biofit/__init__.py
biofit/__main__.py
biofit/config.py
biofit/eval.py
biofit/exceptions.py
biofit/processing.py
biofit/train.py
biofit/train_eval_utils.py
biofit/auto/__init__.py
biofit/auto/auto_factory.py
biofit/auto/configuration_auto.py
biofit/auto/modeling_auto.py
biofit/auto/plotting_auto.py
biofit/auto/processing_auto.py
biofit/cli/__init__.py
biofit/cli/install_r.py
biofit/cli/main.py
biofit/integration/__init__.py
biofit/integration/biosets.py
biofit/integration/R/__init__.py
biofit/integration/R/r_caller.py
biofit/integration/R/scripts/analysis_utils.R
biofit/integration/R/scripts/dependencies.R
biofit/integration/R/scripts/plotting_utils.R
biofit/integration/R/scripts/utils.R
biofit/metrics/__init__.py
biofit/metrics/metrics.py
biofit/models/__init__.py
biofit/models/models.py
biofit/models/ensemble/__init__.py
biofit/models/ensemble/ensemble.py
biofit/models/lasso/__init__.py
biofit/models/lasso/lasso.py
biofit/models/lightgbm/__init__.py
biofit/models/lightgbm/lightgbm.py
biofit/models/logistic_regression/__init__.py
biofit/models/logistic_regression/logistic_regression.py
biofit/models/random_forest/__init__.py
biofit/models/random_forest/random_forest.py
biofit/preprocessing/__init__.py
biofit/preprocessing/encoding/__init__.py
biofit/preprocessing/encoding/encoding.py
biofit/preprocessing/encoding/label_binarizing/__init__.py
biofit/preprocessing/encoding/label_binarizing/label_binarizing.py
biofit/preprocessing/encoding/label_encoding/__init__.py
biofit/preprocessing/encoding/label_encoding/label_encoding.py
biofit/preprocessing/feature_extraction/__init__.py
biofit/preprocessing/feature_extraction/feature_extraction.py
biofit/preprocessing/feature_extraction/plot_feature_extraction.py
biofit/preprocessing/feature_extraction/pca/__init__.py
biofit/preprocessing/feature_extraction/pca/pca.py
biofit/preprocessing/feature_extraction/pca/plot_pca.py
biofit/preprocessing/feature_extraction/pcoa/__init__.py
biofit-0.0.1.dist-info/LICENSE
biofit-0.0.1.dist-info/METADATA
biofit-0.0.1.dist-info/WHEEL
biofit-0.0.1.dist-info/entry_points.txt
biofit-0.0.1.dist-info/top_level.txt
biofit-0.0.1.dist-info/RECORD
