Metadata-Version: 2.1
Name: biofit
Version: 0.0.1
Summary: BioFit: Bioinformatics Machine Learning Framework
Home-page: https://github.com/psmyth94/biofit
Author: Patrick Smyth
Author-email: psmyth1994@gmail.com
License: MIT
Download-URL: https://github.com/psmyth94/biofit/tags
Keywords: omics machine learning bioinformatics metrics
Platform: UNKNOWN
Classifier: Development Status :: 5 - Production/Stable
Classifier: Intended Audience :: Developers
Classifier: Intended Audience :: Education
Classifier: Intended Audience :: Science/Research
Classifier: License :: OSI Approved :: MIT License
Classifier: Operating System :: OS Independent
Classifier: Programming Language :: Python :: 3
Classifier: Programming Language :: Python :: 3.8
Classifier: Programming Language :: Python :: 3.9
Classifier: Programming Language :: Python :: 3.10
Classifier: Programming Language :: Python :: 3.11
Classifier: Topic :: Scientific/Engineering :: Artificial Intelligence
Classifier: Topic :: Scientific/Engineering :: Bio-Informatics
Requires-Python: >=3.8.0,<3.12.0
Requires-Dist: biocore>=1.1.1
Requires-Dist: filelock
Requires-Dist: numpy>=1.17
Requires-Dist: pyarrow>=8.0.0
Requires-Dist: pyarrow-hotfix
Requires-Dist: dill<0.3.8,>=0.3.0
Requires-Dist: pandas
Requires-Dist: requests>=2.19.0
Requires-Dist: tqdm>=4.62.1
Requires-Dist: xxhash
Requires-Dist: multiprocess
Requires-Dist: fsspec[http]<=2023.10.0,>=2023.1.0
Requires-Dist: packaging
Requires-Dist: pyyaml>=5.1
Requires-Dist: scikit-learn
Provides-Extra: all
Requires-Dist: matplotlib; extra == "all"
Requires-Dist: seaborn; extra == "all"
Requires-Dist: psutil; extra == "all"
Requires-Dist: polars>=0.20.5; extra == "all"
Requires-Dist: timezones>=0.10.2; extra == "all"
Requires-Dist: optuna; extra == "all"
Requires-Dist: lightgbm; extra == "all"
Requires-Dist: imbalanced-learn; extra == "all"
Requires-Dist: ruff>=0.1.5; extra == "all"
Requires-Dist: s3fs; extra == "all"
Provides-Extra: apache-beam
Requires-Dist: apache-beam<2.44.0,>=2.26.0; extra == "apache-beam"
Provides-Extra: docs
Requires-Dist: s3fs; extra == "docs"
Provides-Extra: jax
Requires-Dist: jax>=0.3.14; extra == "jax"
Requires-Dist: jaxlib>=0.3.14; extra == "jax"
Provides-Extra: ml
Requires-Dist: polars>=0.20.5; extra == "ml"
Requires-Dist: timezones>=0.10.2; extra == "ml"
Requires-Dist: optuna; extra == "ml"
Requires-Dist: lightgbm; extra == "ml"
Requires-Dist: imbalanced-learn; extra == "ml"
Provides-Extra: polars
Requires-Dist: polars>=0.20.5; extra == "polars"
Requires-Dist: timezones>=0.10.2; extra == "polars"
Provides-Extra: quality
Requires-Dist: ruff>=0.1.5; extra == "quality"
Provides-Extra: rpy2
Requires-Dist: rpy2>=3.5.15; extra == "rpy2"
Requires-Dist: rpy2-arrow>=0.0.8; extra == "rpy2"
Provides-Extra: s3
Requires-Dist: s3fs; extra == "s3"
Provides-Extra: tensorflow
Requires-Dist: tensorflow!=2.6.0,!=2.6.1,>=2.2.0; (sys_platform != "darwin" or platform_machine != "arm64") and extra == "tensorflow"
Requires-Dist: tensorflow-macos; (sys_platform == "darwin" and platform_machine == "arm64") and extra == "tensorflow"
Provides-Extra: tensorflow_gpu
Requires-Dist: tensorflow-gpu!=2.6.0,!=2.6.1,>=2.2.0; extra == "tensorflow-gpu"
Provides-Extra: test
Requires-Dist: ruff>=0.1.5; extra == "test"
Requires-Dist: pytest; extra == "test"
Requires-Dist: pytest-timeout; extra == "test"
Requires-Dist: pytest-xdist; extra == "test"
Requires-Dist: s3fs; extra == "test"
Requires-Dist: matplotlib; extra == "test"
Requires-Dist: seaborn; extra == "test"
Requires-Dist: psutil; extra == "test"
Requires-Dist: polars>=0.20.5; extra == "test"
Requires-Dist: timezones>=0.10.2; extra == "test"
Requires-Dist: optuna; extra == "test"
Requires-Dist: lightgbm; extra == "test"
Requires-Dist: imbalanced-learn; extra == "test"
Provides-Extra: torch
Requires-Dist: torch; extra == "torch"
Provides-Extra: vcf
Requires-Dist: cyvcf2>=0.30.0; extra == "vcf"
Requires-Dist: sgkit>=0.0.1; extra == "vcf"
Provides-Extra: viz
Requires-Dist: matplotlib; extra == "viz"
Requires-Dist: seaborn; extra == "viz"
Requires-Dist: psutil; extra == "viz"
